synthetmic/__init__.py
synthetmic/generate.py
synthetmic/plot.py
synthetmic/utils.py
synthetmic/data/__init__.py
synthetmic/data/paper.py
synthetmic/data/toy.py
synthetmic/data/utils.py
synthetmic-0.1.4.dist-info/METADATA
synthetmic-0.1.4.dist-info/WHEEL
synthetmic-0.1.4.dist-info/licenses/LICENSE
synthetmic-0.1.4.dist-info/RECORD
