Metadata-Version: 2.4
Name: synthetmic
Version: 0.1.4
Summary: A Python package for generating synthetic Laguerre polycrystalline microstructures
Project-URL: homepage, https://github.com/synthetic-microstructures/synthetmic
Project-URL: issues, https://github.com/synthetic-microstructures/synthetmic/issues
Author-email: "R. O. Ibraheem" <ibraheem.abdulrasheed@gmail.com>, "D. P. Bourne" <D.Bourne@hw.ac.uk>, "S. M. Roper" <Steven.Roper@glasgow.ac.uk>
Maintainer-email: "R. O. Ibraheem" <ibraheem.abdulrasheed@gmail.com>, "D. P. Bourne" <D.Bourne@hw.ac.uk>, "S. M. Roper" <Steven.Roper@glasgow.ac.uk>
License-Expression: MIT
License-File: LICENSE
Classifier: Operating System :: OS Independent
Classifier: Programming Language :: Python
Classifier: Programming Language :: Python :: 3
Classifier: Programming Language :: Python :: 3.11
Classifier: Programming Language :: Python :: 3.12
Classifier: Programming Language :: Python :: 3.13
Requires-Python: >=3.11
Requires-Dist: matplotlib>=3.10.3
Requires-Dist: numpy>=2.3.0
Requires-Dist: pysdot==0.2.38
Requires-Dist: pyvista[jupyter]>=0.45.2
Requires-Dist: scipy>=1.15.3
Requires-Dist: vtk>=9.4.2
Provides-Extra: cli
Requires-Dist: click>=8.2.1; extra == 'cli'
Provides-Extra: examples
Provides-Extra: tests
Requires-Dist: pytest>=8.4.1; extra == 'tests'
